{
  "timestamp": "2026-03-08T14:51:09.440537+01:00",
  "saunas": [
    {
      "name": "Sauna rechts",
      "current_seats": 24,
      "max_seats": 40,
      "occupancy_percent": 60.0,
      "capacity_message": "Mir si guet bsuecht. | Quite busy"
    }
  ],
  "weather": {
    "temperature": 15.7,
    "apparent_temperature": 13.9,
    "humidity": 51,
    "precipitation": 0.0,
    "weather_code": 1,
    "weather_description": "\u00dcberwiegend klar | Mainly clear",
    "cloud_cover": 0,
    "is_rainy": false,
    "is_sunny": true
  }
}