{
  "timestamp": "2026-02-22T10:15:25.136001+01:00",
  "saunas": [
    {
      "name": "Sauna rechts",
      "current_seats": 16,
      "max_seats": 40,
      "occupancy_percent": 40.0,
      "capacity_message": "Es het g\u00e4big Platz. | Plenty of space."
    }
  ],
  "weather": {
    "temperature": 5.2,
    "apparent_temperature": 3.3,
    "humidity": 86,
    "precipitation": 0.0,
    "weather_code": 3,
    "weather_description": "Bew\u00f6lkt | Overcast",
    "cloud_cover": 95,
    "is_rainy": false,
    "is_sunny": false
  }
}