{
  "timestamp": "2026-02-20T15:00:46.873615+01:00",
  "saunas": [
    {
      "name": "Sauna rechts",
      "current_seats": 43,
      "max_seats": 40,
      "occupancy_percent": 107.5,
      "capacity_message": "Pr\u00e4tschvou und es git e Wartezyt. | Full with a waiting time."
    }
  ],
  "weather": {
    "temperature": 6.9,
    "apparent_temperature": 4.6,
    "humidity": 77,
    "precipitation": 0.0,
    "weather_code": 61,
    "weather_description": "Leichter Regen | Slight rain",
    "cloud_cover": 100,
    "is_rainy": true,
    "is_sunny": false
  }
}