{
  "timestamp": "2026-03-17T13:34:31.920606+01:00",
  "saunas": [
    {
      "name": "Sauna rechts",
      "current_seats": 26,
      "max_seats": 40,
      "occupancy_percent": 65.0,
      "capacity_message": "Mir si guet bsuecht. | Quite busy"
    }
  ],
  "weather": {
    "temperature": 12.2,
    "apparent_temperature": 9.2,
    "humidity": 47,
    "precipitation": 0.0,
    "weather_code": 1,
    "weather_description": "\u00dcberwiegend klar | Mainly clear",
    "cloud_cover": 39,
    "is_rainy": false,
    "is_sunny": false
  }
}