{
  "timestamp": "2026-02-21T20:30:34.583568+01:00",
  "saunas": [
    {
      "name": "Sauna rechts",
      "current_seats": 21,
      "max_seats": 40,
      "occupancy_percent": 52.5,
      "capacity_message": "Es het g\u00e4big Platz. | Plenty of space."
    }
  ],
  "weather": {
    "temperature": 6.5,
    "apparent_temperature": 4.4,
    "humidity": 82,
    "precipitation": 0.0,
    "weather_code": 0,
    "weather_description": "Klar | Clear",
    "cloud_cover": 0,
    "is_rainy": false,
    "is_sunny": true
  }
}