{
  "timestamp": "2026-02-06T20:09:00.277962+01:00",
  "saunas": [
    {
      "name": "Sauna rechts",
      "current_seats": 31,
      "max_seats": 40,
      "occupancy_percent": 77.5,
      "capacity_message": "Mir si guet bsuecht. | Quite busy"
    },
    {
      "name": "Sauna",
      "current_seats": 41,
      "max_seats": 40,
      "occupancy_percent": 102.5,
      "capacity_message": "Pr\u00e4tschvou und es git e Wartezyt. | Full with a waiting time."
    }
  ],
  "weather": {
    "temperature": 6.3,
    "apparent_temperature": 3.8,
    "humidity": 81,
    "precipitation": 0.0,
    "weather_code": 80,
    "weather_description": "Leichte Regenschauer | Slight rain showers",
    "cloud_cover": 99,
    "is_rainy": true,
    "is_sunny": false
  }
}